shinylive_deploy/app.py
shinylive_deploy/config.py
shinylive_deploy/process/__init__.py
shinylive_deploy/process/base.py
shinylive_deploy/process/local.py
shinylive_deploy/process/server.py
shinylive_deploy-2024.8.8.dist-info/METADATA
shinylive_deploy-2024.8.8.dist-info/WHEEL
shinylive_deploy-2024.8.8.dist-info/entry_points.txt
shinylive_deploy-2024.8.8.dist-info/top_level.txt
shinylive_deploy-2024.8.8.dist-info/RECORD
