Metadata-Version: 2.1
Name: shinylive-deploy
Version: 2024.8.8
Summary: CLI utility to help deploy py-shinylive apps to hosted webservers via SSH.
Author-email: darrida <darrida.py@gmail.com>
Project-URL: Homepage, https://github.com/darrida/py-shinylive-deploy-webserver
Project-URL: Issues, https://github.com/darrida/py-shinylive-deploy-webserver/issues
Requires-Dist: shiny
Requires-Dist: shinylive
Requires-Dist: gitpython
Requires-Dist: paramiko
Requires-Dist: pydantic <2.0
Provides-Extra: tests
Requires-Dist: fastapi ; extra == 'tests'
Requires-Dist: pytest ; extra == 'tests'
Requires-Dist: loguru ; extra == 'tests'
Requires-Dist: pyfetch-mimic ==2024.06.14 ; extra == 'tests'
Requires-Dist: httpx ; extra == 'tests'
Requires-Dist: shinyswatch ; extra == 'tests'
